{
  "category": "SwingTrade",
  "metrics": {
    "category": "SwingTrade",
    "auc": 0.6856640751653271,
    "precision": 0.2416170078864043,
    "recall": 0.6408544378080906,
    "f1": 0.3509265540757668,
    "val_loss": 0.583,
    "best_epoch": 8,
    "total_epochs": 18,
    "train_samples": 985179,
    "val_samples": 246295,
    "training_time_sec": 2444.8,
    "device": "cuda",
    "pos_weight": 5.0868
  },
  "config": {
    "hidden_size_1": 64,
    "hidden_size_2": 32,
    "dropout": 0.3,
    "sequence_length": 20,
    "batch_size": 32,
    "learning_rate": 0.001,
    "epochs": 50,
    "patience": 10
  }
}